ruotvet/__init__.py
ruotvet/clients/__init__.py
ruotvet/clients/exceptions.py
ruotvet/clients/brainly/__init__.py
ruotvet/clients/brainly/core.py
ruotvet/clients/chemequations/__init__.py
ruotvet/clients/chemequations/core.py
ruotvet/clients/gdz/__init__.py
ruotvet/clients/gdz/core.py
ruotvet/clients/mailru/__init__.py
ruotvet/clients/mailru/core.py
ruotvet/clients/superresheba/__init__.py
ruotvet/clients/superresheba/core.py
ruotvet/clients/yandexq/__init__.py
ruotvet/clients/yandexq/core.py
ruotvet/http/__init__.py
ruotvet/http/core.py
ruotvet/types/__init__.py
ruotvet/types/base.py
ruotvet/utils/__init__.py
ruotvet/utils/attachments.py
ruotvet/utils/google.py
ruotvet/utils/ocr.py
ruotvet-1.3.1.1.dist-info/LICENSE
ruotvet-1.3.1.1.dist-info/METADATA
ruotvet-1.3.1.1.dist-info/WHEEL
ruotvet-1.3.1.1.dist-info/top_level.txt
ruotvet-1.3.1.1.dist-info/RECORD
