Metadata-Version: 2.1
Name: ruotvet
Version: 1.3.1.1
Summary: Library for searching answers to school questions.
Home-page: https://github.com/rgit/ruotvet/
Author: Kirill Feschenko
Author-email: swipduces@yandex.com
License: GNU LGPLv3
Project-URL: Documentation, https://github.com/rgit/ruotvet/blob/master/README.md
Project-URL: Issues, https://github.com/rgit/ruotvet/issues
Keywords: gdz brainly otvet.mail.ru thequestion resheba
Platform: UNKNOWN
Classifier: License :: OSI Approved :: GNU Lesser General Public License v3 (LGPLv3)
Classifier: Programming Language :: Python
Classifier: Programming Language :: Python :: 3
Classifier: Programming Language :: Python :: 3.7
Classifier: Programming Language :: Python :: 3.8
Classifier: Programming Language :: Python :: 3.9
Classifier: Intended Audience :: Developers
Classifier: Operating System :: OS Independent
Classifier: Programming Language :: Python :: Implementation :: CPython
Classifier: Programming Language :: Python :: Implementation :: PyPy
Classifier: Topic :: Scientific/Engineering :: Image Recognition
Classifier: Topic :: Utilities
Classifier: Topic :: Education
Classifier: Typing :: Typed
Requires-Python: >=3.7.0
Requires-Dist: aiohttp
Requires-Dist: aiofiles
Requires-Dist: beautifulsoup4
Requires-Dist: pydantic
Provides-Extra: ocr
Requires-Dist: opencv-python (~=4.2.0.34) ; extra == 'ocr'
Requires-Dist: pytesseract (~=0.3.2) ; extra == 'ocr'
